MANIFEST.in
README.md
requirements.txt
setup.py
Asi/__init__.py
Asi/api.py
Asi/callback.py
Asi.egg-info/PKG-INFO
Asi.egg-info/SOURCES.txt
Asi.egg-info/dependency_links.txt
Asi.egg-info/not-zip-safe
Asi.egg-info/requires.txt
Asi.egg-info/top_level.txt