Metadata-Version: 2.1
Name: Asi
Version: 1.2.1
Summary: Ansible Api Warpper
Home-page: https://github.com/idweball/Asi
Author: loveshell
Author-email: idweball@gmail.com
License: BSD
Platform: UNKNOWN
